odoo/addons/stock_lot_filter_available/README.rst
odoo/addons/stock_lot_filter_available/__init__.py
odoo/addons/stock_lot_filter_available/__manifest__.py
odoo/addons/stock_lot_filter_available/i18n/es.po
odoo/addons/stock_lot_filter_available/i18n/stock_lot_filter_available.pot
odoo/addons/stock_lot_filter_available/models/__init__.py
odoo/addons/stock_lot_filter_available/models/stock_production_lot.py
odoo/addons/stock_lot_filter_available/readme/CONTRIBUTORS.rst
odoo/addons/stock_lot_filter_available/readme/DESCRIPTION.rst
odoo/addons/stock_lot_filter_available/readme/USAGE.rst
odoo/addons/stock_lot_filter_available/static/description/icon.png
odoo/addons/stock_lot_filter_available/static/description/index.html
odoo/addons/stock_lot_filter_available/tests/__init__.py
odoo/addons/stock_lot_filter_available/tests/test_stock_lot_filter_available.py
odoo/addons/stock_lot_filter_available/views/stock_production_lot_views.xml
odoo13_addon_stock_lot_filter_available-13.0.2.0.0.dist-info/METADATA
odoo13_addon_stock_lot_filter_available-13.0.2.0.0.dist-info/WHEEL
odoo13_addon_stock_lot_filter_available-13.0.2.0.0.dist-info/top_level.txt
odoo13_addon_stock_lot_filter_available-13.0.2.0.0.dist-info/RECORD
